{
  "Name": "Talk8343",
  "Blocks": [
    {
      "ItemID": 101,
      "Name": "Splash",
      "Description": "Splash",
      "Position": "(-2434.278,-1224.476)",
      "Commands": [
        {
          "ItemID": 147,
          "CmdType": "Fungus.TryinitFungaus"
        },
        {
          "ItemID": 240,
          "CmdType": "Fungus.CallMethod"
        },
        {
          "ItemID": 86,
          "CmdType": "Fungus.Call",
          "targetFlowchartName": null,
          "targetBlockID": "154(赋值)",
          "startLabel": "",
          "startIndex": 0,
          "callMode": 0
        }
      ]
    },
    {
      "ItemID": 304,
      "Name": "New Block",
      "Description": "New Block",
      "Position": "(-2789.389,-951.4227)",
      "Commands": [
        {
          "ItemID": 369,
          "CmdType": "Fungus.SetStaticValue"
        },
        {
          "ItemID": 370,
          "CmdType": "CmdRefreshNPCUI"
        }
      ]
    },
    {
      "ItemID": 391,
      "Name": "放入信物",
      "Description": "放入信物",
      "Position": "(-2427.039,-852.5989)",
      "Commands": [
        {
          "ItemID": 396,
          "CmdType": "Fungus.Say",
          "AvatarIDInt": 0,
          "AvatarBindKey": "",
          "StoryText": "阴阳两气汇聚在一起没入地面。“咔咔咔”一阵机关响动之后，地面露出一道门。",
          "Description": "",
          "AvatarIDSetType": "Normal"
        },
        {
          "ItemID": 399,
          "CmdType": "Fungus.ItemRemove"
        },
        {
          "ItemID": 397,
          "CmdType": "Fungus.SetVariable"
        },
        {
          "ItemID": 398,
          "CmdType": "Fungus.LoadFuBen"
        }
      ]
    },
    {
      "ItemID": 243,
      "Name": "剧情",
      "Description": "剧情",
      "Position": "(-2436.568,-1039.307)",
      "Commands": [
        {
          "ItemID": 371,
          "CmdType": "Fungus.Say",
          "AvatarIDInt": 1,
          "AvatarBindKey": "",
          "StoryText": "天阴阁，这位前辈的起名字可真偷懒。",
          "Description": "",
          "AvatarIDSetType": "Normal"
        },
        {
          "ItemID": 392,
          "CmdType": "Fungus.Menu",
          "Text": "推门而入",
          "TargetBlockID": "this:390(推门而入)"
        }
      ]
    },
    {
      "ItemID": 390,
      "Name": "推门而入",
      "Description": "推门而入",
      "Position": "(-2428.215,-952.5988)",
      "Commands": [
        {
          "ItemID": 393,
          "CmdType": "Fungus.Say",
          "AvatarIDInt": 0,
          "AvatarBindKey": "",
          "StoryText": "眼前只有一个石台，上面的凹槽正好可以放入你在幻阳境得到的信物。",
          "Description": "",
          "AvatarIDSetType": "Normal"
        },
        {
          "ItemID": 394,
          "CmdType": "Fungus.Say",
          "AvatarIDInt": 1,
          "AvatarBindKey": "",
          "StoryText": "和之前的天阳阁一样，这里也不是这机关城的核心。",
          "Description": "",
          "AvatarIDSetType": "Normal"
        },
        {
          "ItemID": 395,
          "CmdType": "Fungus.Menu",
          "Text": "放入信物",
          "TargetBlockID": "this:391(放入信物)"
        }
      ]
    },
    {
      "ItemID": 154,
      "Name": "赋值",
      "Description": "赋值",
      "Position": "(-2439.469,-1134.91)",
      "Commands": [
        {
          "ItemID": 389,
          "CmdType": "Fungus.SetStaticValue"
        },
        {
          "ItemID": 244,
          "CmdType": "Fungus.Call",
          "targetFlowchartName": null,
          "targetBlockID": "243(剧情)",
          "startLabel": "",
          "startIndex": 0,
          "callMode": 0
        }
      ]
    }
  ],
  "Variables": []
}